bugyi/dummy/__init__.py
bugyi/dummy/cli.py
bugyi.dummy-0.3.3.dist-info/METADATA
bugyi.dummy-0.3.3.dist-info/WHEEL
bugyi.dummy-0.3.3.dist-info/entry_points.txt
bugyi.dummy-0.3.3.dist-info/top_level.txt
bugyi.dummy-0.3.3.dist-info/RECORD
